gdmmt/__init__.py
gdmmt/cli.py
gdmmt-0.1.5.dist-info/licenses/LICENSE
gdmmt-0.1.5.dist-info/METADATA
gdmmt-0.1.5.dist-info/WHEEL
gdmmt-0.1.5.dist-info/entry_points.txt
gdmmt-0.1.5.dist-info/top_level.txt
gdmmt-0.1.5.dist-info/RECORD
