Metadata-Version: 2.4
Name: gdmmt
Version: 0.1.5
Summary: GD MMT: Extended version of mmt cli. Handles SRI generation, prefix management, versioning, and commit message generation.
Author-email: Glendale Designs <info@glendaledesigns.com>
License: Copyright (C) Glendale Designs, Inc - All Rights Reserved
License-File: LICENSE
Dynamic: license-file
